openedx2zim/VERSION
openedx2zim/__init__.py
openedx2zim/__main__.py
openedx2zim/annex.py
openedx2zim/constants.py
openedx2zim/entrypoint.py
openedx2zim/html_processor.py
openedx2zim/instance_connection.py
openedx2zim/scraper.py
openedx2zim/utils.py
openedx2zim/templates/DragAndDropV2.html
openedx2zim/templates/audio_player.html
openedx2zim/templates/base.html
openedx2zim/templates/booknav.html
openedx2zim/templates/chapter_menu.html
openedx2zim/templates/course_menu.html
openedx2zim/templates/discussion.html
openedx2zim/templates/forum.html
openedx2zim/templates/forum_article.html
openedx2zim/templates/freetextresponse.html
openedx2zim/templates/home.html
openedx2zim/templates/menu.html
openedx2zim/templates/post.html
openedx2zim/templates/problem.html
openedx2zim/templates/side_menu.html
openedx2zim/templates/specific_page.html
openedx2zim/templates/thread.html
openedx2zim/templates/vertical.html
openedx2zim/templates/video.html
openedx2zim/templates/wiki_list.html
openedx2zim/templates/wiki_list_none.html
openedx2zim/templates/wiki_page.html
openedx2zim/templates/assets/audio_default.png
openedx2zim/templates/assets/jquery.min.js
openedx2zim/templates/assets/main.css
openedx2zim/templates/assets/mooc.js
openedx2zim/templates/assets/thread.css
openedx2zim/templates/assets/videojs-ogvjs.js
openedx2zim/templates/assets/xblocks.js
openedx2zim/templates/assets/zim_prefix.js
openedx2zim/templates/assets/fontawesome/css/all.css
openedx2zim/templates/assets/fontawesome/css/all.min.css
openedx2zim/templates/assets/fontawesome/css/brands.css
openedx2zim/templates/assets/fontawesome/css/brands.min.css
openedx2zim/templates/assets/fontawesome/css/fontawesome.css
openedx2zim/templates/assets/fontawesome/css/fontawesome.min.css
openedx2zim/templates/assets/fontawesome/css/regular.css
openedx2zim/templates/assets/fontawesome/css/regular.min.css
openedx2zim/templates/assets/fontawesome/css/solid.css
openedx2zim/templates/assets/fontawesome/css/solid.min.css
openedx2zim-1.0.1.dist-info/LICENSE
openedx2zim-1.0.1.dist-info/METADATA
openedx2zim-1.0.1.dist-info/WHEEL
openedx2zim-1.0.1.dist-info/entry_points.txt
openedx2zim-1.0.1.dist-info/top_level.txt
openedx2zim-1.0.1.dist-info/RECORD
