Metadata-Version: 2.1
Name: openedx2zim
Version: 1.0.1
Summary: Turn MOOCs on openedx instances into ZIMs
Home-page: https://github.com/openzim/openedx
Author: dattaz
Author-email: taz@dattaz.fr
License: GPLv3+
Keywords: kiwix zim openedx offline
Platform: UNKNOWN
Classifier: Development Status :: 4 - Beta
Classifier: Intended Audience :: Developers
Classifier: Programming Language :: Python
Classifier: Programming Language :: Python :: 3.8
Classifier: License :: OSI Approved :: GNU General Public License v3 or later (GPLv3+)
Requires-Python: >=3.6
Requires-Dist: beautifulsoup4 (<4.10,>=4.9.0)
Requires-Dist: lxml (<4.6,>=4.5.1)
Requires-Dist: webvtt-py (<0.5,>=0.4.5)
Requires-Dist: python-slugify (<4.1,>=4.0.0)
Requires-Dist: Jinja2 (<2.12,>=2.11.2)
Requires-Dist: mistune (<2.1,>=2.0.0a4)
Requires-Dist: requests (<3.0,>=2.24)
Requires-Dist: iso-639 (<0.5,>=0.4.5)
Requires-Dist: zimscraperlib (<1.4,>=1.3.6)
Requires-Dist: kiwixstorage (<1.0,>=0.3)
Requires-Dist: pif (<0.9,>=0.8.2)
Requires-Dist: xxhash (<2.1,>=2.0.0)
Requires-Dist: youtube-dl
